napari_tissue_cuboid_analysis/__init__.py
napari_tissue_cuboid_analysis/_utils.py
napari_tissue_cuboid_analysis/_version.py
napari_tissue_cuboid_analysis/_widget.py
napari_tissue_cuboid_analysis/napari.yaml
napari_tissue_cuboid_analysis-0.0.8.dist-info/licenses/LICENSE
napari_tissue_cuboid_analysis-0.0.8.dist-info/METADATA
napari_tissue_cuboid_analysis-0.0.8.dist-info/WHEEL
napari_tissue_cuboid_analysis-0.0.8.dist-info/entry_points.txt
napari_tissue_cuboid_analysis-0.0.8.dist-info/top_level.txt
napari_tissue_cuboid_analysis-0.0.8.dist-info/RECORD
